metlo/__init__.py
metlo/django.py
metlo/fastapi.py
metlo/flask.py
metlo/utils.py
metlo-0.1.5.dist-info/METADATA
metlo-0.1.5.dist-info/WHEEL
metlo-0.1.5.dist-info/top_level.txt
metlo-0.1.5.dist-info/RECORD
