Metadata-Version: 2.1
Name: metlo
Version: 0.1.5
Summary: The Python Agent for Metlo
Home-page: https://www.metlo.com
License: MIT
Project-URL: Documentation, https://docs.metlo.com/docs/python
Project-URL: Source Code, https://github.com/metlo-labs/metlo/
Project-URL: Issue Tracker, https://github.com/metlo-labs/metlo/issues/
Project-URL: Twitter, https://mobile.twitter.com/metlohq
Project-URL: Chat, https://discord.gg/gasqPDKEAC
Classifier: Development Status :: 3 - Alpha
Classifier: Intended Audience :: Developers
Classifier: Operating System :: MacOS :: MacOS X
Classifier: Operating System :: Microsoft :: Windows
Classifier: Operating System :: POSIX :: Linux
Classifier: License :: OSI Approved :: MIT License
Classifier: Programming Language :: Python :: 3.7
Classifier: Programming Language :: Python :: 3.8
Classifier: Programming Language :: Python :: 3.9
Classifier: Programming Language :: Python :: 3.10
Classifier: Programming Language :: Python :: 3.11
Classifier: Programming Language :: Python :: 3.12
Requires-Python: >=3.7
Requires-Dist: metlo-python-agent-bindings-common (==0.0.2)
